linodeapi.py
setup.py
linodeapi.egg-info/PKG-INFO
linodeapi.egg-info/SOURCES.txt
linodeapi.egg-info/dependency_links.txt
linodeapi.egg-info/top_level.txt