Metadata-Version: 1.1
Name: linodeapi
Version: 1.8
Summary: Python API for Linode DNS management
Home-page: https://github.com/RevelSystems/linodeapi
Author: RevelSystems
Author-email: devops@revelsystems.com
License: UNKNOWN
Platform: UNKNOWN
Classifier: Programming Language :: Python :: 2
